clear_linux/__init__.py
clear_linux/clear_linux.py
clear_linux-1.0.4.dist-info/METADATA
clear_linux-1.0.4.dist-info/WHEEL
clear_linux-1.0.4.dist-info/licenses/LICENSE
clear_linux-1.0.4.dist-info/RECORD
